memento/__init__.py
memento/memento.py
memento_scorecard-2.0.3.dist-info/LICENSE
memento_scorecard-2.0.3.dist-info/METADATA
memento_scorecard-2.0.3.dist-info/WHEEL
memento_scorecard-2.0.3.dist-info/top_level.txt
memento_scorecard-2.0.3.dist-info/RECORD
