Metadata-Version: 2.1
Name: memento-scorecard
Version: 2.0.3
Summary: Scorecard development with Python
Home-page: https://github.com/Guilliu/Memento
Author: Guillermo Lizcano Villafáñez
Author-email: guille.lv.97@gmail.com
License: Apache License 2.0
Keywords: python,scoring,rating,logistic,regression,scorecard,woe,credit-risk,autogrouping
Classifier: Programming Language :: Python :: 3
Classifier: License :: OSI Approved :: Apache Software License
Classifier: Operating System :: OS Independent
Classifier: Development Status :: 5 - Production/Stable
License-File: LICENSE
